odoo/addons/stock_owner_restriction/README.rst
odoo/addons/stock_owner_restriction/__init__.py
odoo/addons/stock_owner_restriction/__manifest__.py
odoo/addons/stock_owner_restriction/i18n/es.po
odoo/addons/stock_owner_restriction/i18n/it.po
odoo/addons/stock_owner_restriction/i18n/nl.po
odoo/addons/stock_owner_restriction/i18n/pt.po
odoo/addons/stock_owner_restriction/i18n/pt_BR.po
odoo/addons/stock_owner_restriction/i18n/stock_owner_restriction.pot
odoo/addons/stock_owner_restriction/models/__init__.py
odoo/addons/stock_owner_restriction/models/product.py
odoo/addons/stock_owner_restriction/models/stock_move.py
odoo/addons/stock_owner_restriction/models/stock_picking.py
odoo/addons/stock_owner_restriction/models/stock_picking_type.py
odoo/addons/stock_owner_restriction/models/stock_quant.py
odoo/addons/stock_owner_restriction/readme/CONFIGURE.md
odoo/addons/stock_owner_restriction/readme/CONTRIBUTORS.md
odoo/addons/stock_owner_restriction/readme/DESCRIPTION.md
odoo/addons/stock_owner_restriction/readme/USAGE.md
odoo/addons/stock_owner_restriction/static/description/icon.png
odoo/addons/stock_owner_restriction/static/description/index.html
odoo/addons/stock_owner_restriction/tests/__init__.py
odoo/addons/stock_owner_restriction/tests/test_stock_owner_restriction.py
odoo/addons/stock_owner_restriction/views/stock_picking_type_views.xml
odoo/addons/stock_owner_restriction/views/stock_picking_views.xml
odoo_addon_stock_owner_restriction-18.0.1.0.0.7.dist-info/METADATA
odoo_addon_stock_owner_restriction-18.0.1.0.0.7.dist-info/WHEEL
odoo_addon_stock_owner_restriction-18.0.1.0.0.7.dist-info/top_level.txt
odoo_addon_stock_owner_restriction-18.0.1.0.0.7.dist-info/RECORD
